docs/source/conf.py
requirements/requirements.build.txt
requirements/requirements.dev.txt
requirements/requirements.doc.txt
requirements/requirements.test.txt
requirements/requirements.txt
templafirm/__init__.py
templafirm/py.typed
templafirm/core/__init__.py
templafirm/core/meta_table.py
templafirm/core/provider.py
templafirm/core/templater.py
templafirm/gke/__init__.py
templafirm/gke/gke_provider.py
templafirm/gke/modules/mrdma_node_pool/main.tf
templafirm/gke/modules/mrdma_node_pool/variables.tf
templafirm/gke/templates/__init__.py
templafirm/gke/templates/gke_provider_meta.yaml
templafirm/gke/templates/node_pools/mrdma_node_pool.jinja2
templafirm-0.0.13.dist-info/licenses/LICENSE
test/__init__.py
test/assets/__init__.py
test/integration/__init__.py
test/integration/gke/__init__.py
test/integration/gke/test_mrmda_node_pool.py
test/unit/__init__.py
test/unit/core/__init__.py
test/unit/core/test_provider.py
test/unit/core/test_templater.py
test/unit/gke/test_gke_provider.py
test/unit/gke/test_gke_templates.py
templafirm-0.0.13.dist-info/METADATA
templafirm-0.0.13.dist-info/WHEEL
templafirm-0.0.13.dist-info/top_level.txt
templafirm-0.0.13.dist-info/RECORD
