Metadata-Version: 2.4
Name: templafirm
Version: 0.0.13
Author-email: Max Wierz <weirzmax@gmail.com>
Requires-Python: >=3.8
License-File: LICENSE
Requires-Dist: pyyaml<7,>=6.0.2
Requires-Dist: jinja2<4,>=3.1.6
Provides-Extra: build
Requires-Dist: build<2,>=1.2.2.post1; extra == "build"
Requires-Dist: twine<7,>=6.1.0; extra == "build"
Provides-Extra: dev
Requires-Dist: mypy<2,>=1.14.0; extra == "dev"
Requires-Dist: ruff<1,>=0.11.7; extra == "dev"
Requires-Dist: types-PyYAML<7,>=6.0.12.20241230; extra == "dev"
Provides-Extra: docs
Requires-Dist: sphinx<9,>=7.1.2; extra == "docs"
Requires-Dist: pydata-sphinx-theme<1,>=0.14.1; extra == "docs"
Provides-Extra: test
Requires-Dist: pytest<9,>=8.3.5; extra == "test"
Requires-Dist: pytest-asyncio<1,>=0.24.0; extra == "test"
Requires-Dist: tftest<2,>=1.8.5; extra == "test"
Dynamic: license-file
